chromedriverupdate/__init__.py
chromedriverupdate/chrome_driver.py
chromedriverupdate-1.0.0.dist-info/LICENSE
chromedriverupdate-1.0.0.dist-info/METADATA
chromedriverupdate-1.0.0.dist-info/WHEEL
chromedriverupdate-1.0.0.dist-info/top_level.txt
chromedriverupdate-1.0.0.dist-info/RECORD
