Metadata-Version: 2.1
Name: chromedriverupdate
Version: 1.0.0
Summary: Update chrome driver
Home-page: https://github.com/kirikumo/chromedriverupdate
Author: cghn
License: GPLv3
Requires-Python: >=3.7
License-File: LICENSE
Requires-Dist: requests (>=2.25.1)
